<annotation>
	<folder>results</folder>
	<filename>type_1_side_1(15).jpg</filename>
	<path>/home/afshin/PycharmProjects/test/card/results/type_1_side_1(15).jpg</path>
	<source>
		<database>Unknown</database>
	</source>
	<size>
		<width>750</width>
		<height>500</height>
		<depth>3</depth>
	</size>
	<segmented>0</segmented>
	<object>
		<name>card_name</name>
		<pose>Unspecified</pose>
		<truncated>0</truncated>
		<difficult>0</difficult>
		<bndbox>
			<xmin>123</xmin>
			<ymin>119</ymin>
			<xmax>634</xmax>
			<ymax>185</ymax>
		</bndbox>
	</object>
	<object>
		<name>card_nic</name>
		<pose>Unspecified</pose>
		<truncated>0</truncated>
		<difficult>0</difficult>
		<bndbox>
			<xmin>63</xmin>
			<ymin>207</ymin>
			<xmax>455</xmax>
			<ymax>274</ymax>
		</bndbox>
	</object>
	<object>
		<name>card_vin</name>
		<pose>Unspecified</pose>
		<truncated>0</truncated>
		<difficult>0</difficult>
		<bndbox>
			<xmin>21</xmin>
			<ymin>282</ymin>
			<xmax>512</xmax>
			<ymax>355</ymax>
		</bndbox>
	</object>
	<object>
		<name>card_number</name>
		<pose>Unspecified</pose>
		<truncated>0</truncated>
		<difficult>0</difficult>
		<bndbox>
			<xmin>294</xmin>
			<ymin>376</ymin>
			<xmax>652</xmax>
			<ymax>481</ymax>
		</bndbox>
	</object>
</annotation>
